Workbook

Sheet Припущення
A1: Фінансова модель бізнес-плану ФОП Федоренко Т. А., версія 2 (допоміжний файл — не подається до заяви)
A2: Жовті клітинки — вхідні дані, які можна змінювати; решта аркушів перераховуються автоматично.
A3: Параметр | B3: Значення | C3: Коментар
A4: Сума гранту, грн | B4: 1000000 | C4: п. 6 Порядку: 500 000–1 500 000 для масштабування без надбавок
A5: Строк проєкту, місяців | B5: 36 | C5: 24 / 36 / 60
A6: Ставка ЄП (3 група, без ПДВ) | B6: 0.05 | C6: п. 293.3 ПКУ
A7: Військовий збір ФОП 3 групи | B7: 0.01 | C7: 1 % доходу (п. 16-1 підрозд. 10 розд. XX ПКУ)
A8: ПДФО із зарплати | B8: 0.18 | C8: 18 %
A9: Військовий збір із зарплати | B9: 0.05 | C9: 5 %
A10: ЄСВ роботодавця | B10: 0.22 | C10: 22 %
A11: Мінімальна зарплата (прогноз 2027) | B11: 9546 | C11: проєкт Держбюджету-2027; у 2026 році — 8 647 грн
A12: ЄСВ ФОП за себе, грн/міс | B12: =B10*B9 -> 0.011 | C12: 22 % мінімальної зарплати
A13: Зарплата: консультант з комплаєнсу (рік 1 / 2 / 3) | B13: 25 000 / 27 500 / 30 000 | C13: нарахована, грн/міс
A14: Зарплата: аналітик-адміністратор (рік 1 / 2 / 3) | B14: 20 000 / 22 500 / 25 000 | C14: нарахована, грн/міс
A15: Оренда офісу, грн/міс | B15: 15000 | C15: М1–М12 сплачено наперед з гранту; далі з доходу
A16: Власні кошти: навчання ICA, грн | B16: 385860 | C16: 110 000 у М1 + 275 860 у М13
A17: Власні кошти: оборотний резерв, грн | B17: 100000 | C17: М1; підтвердити випискою

Sheet Пакети і продажі
A1: Код | B1: Пакет послуг | C1: Ціна, грн | D1: Норматив годин | E1: Результат для клієнта
A2: A | B2: Комплаєнс-діагностика (експрес-оцінка процесів, звіт з рекомендаціями) | C2: 25000 | D2: 30 | E2: звіт про відповідність процесів з переліком ризиків і планом усунення
A3: B | B3: Антикорупційна програма / пакет політик і процедур «під ключ» | C3: 45000 | D3: 50 | E3: затверджена антикорупційна програма / політики, регламенти, наказ про уповноваженого
A4: C | B4: Перевірка контрагента (звіт з відкритих реєстрів і санкційних списків) | C4: 2500 | D4: 2.5 | E4: звіт з реєстрів ЄДР, судових рішень, санкційних списків, податкового боргу
A5: D | B5: Навчання персоналу клієнта (тренінг / вебінар, 4 год) | C5: 12000 | D5: 12 | E5: проведений тренінг, матеріали, тест, протокол навчання
A6: E | B6: Абонентський супровід (комплаєнс-офіцер на аутсорсингу), на місяць | C6: 15000 | D6: 19 | E6: щомісячний моніторинг, перевірки контрагентів, консультації, підготовка до перевірок
A9: Місяць | B9: A, шт | C9: B, шт | D9: C, шт | E9: D, шт | F9: E, клієнтів | G9: Дохід основні (A+B+E) | H9: Дохід додаткові (C+D) | I9: Разом дохід, грн | J9: Годин навантаження
A10: 1 | B10: 1 | C10: 0 | D10: 4 | E10: 1 | F10: 1 | G10: =B10*$C$2+C10*$C$3+F10*$C$6 -> 40000 | H10: =D10*$C$4+E10*$C$5 -> 22000 | I10: =G10+H10 -> 62000 | J10: =B10*$D$2+C10*$D$3+D10*$D$4+E10*$D$5+F10*$D$6 -> 71
A11: 2 | B11: 1 | C11: 0 | D11: 4 | E11: 1 | F11: 1 | G11: =B11*$C$2+C11*$C$3+F11*$C$6 -> 40000 | H11: =D11*$C$4+E11*$C$5 -> 22000 | I11: =G11+H11 -> 62000 | J11: =B11*$D$2+C11*$D$3+D11*$D$4+E11*$D$5+F11*$D$6 -> 71
A12: 3 | B12: 1 | C12: 0 | D12: 4 | E12: 1 | F12: 2 | G12: =B12*$C$2+C12*$C$3+F12*$C$6 -> 55000 | H12: =D12*$C$4+E12*$C$5 -> 22000 | I12: =G12+H12 -> 77000 | J12: =B12*$D$2+C12*$D$3+D12*$D$4+E12*$D$5+F12*$D$6 -> 90
A13: 4 | B13: 1 | C13: 0 | D13: 4 | E13: 1 | F13: 2 | G13: =B13*$C$2+C13*$C$3+F13*$C$6 -> 55000 | H13: =D13*$C$4+E13*$C$5 -> 22000 | I13: =G13+H13 -> 77000 | J13: =B13*$D$2+C13*$D$3+D13*$D$4+E13*$D$5+F13*$D$6 -> 90
A14: 5 | B14: 1 | C14: 0 | D14: 4 | E14: 1 | F14: 2 | G14: =B14*$C$2+C14*$C$3+F14*$C$6 -> 55000 | H14: =D14*$C$4+E14*$C$5 -> 22000 | I14: =G14+H14 -> 77000 | J14: =B14*$D$2+C14*$D$3+D14*$D$4+E14*$D$5+F14*$D$6 -> 90
A15: 6 | B15: 1 | C15: 1 | D15: 4 | E15: 1 | F15: 3 | G15: =B15*$C$2+C15*$C$3+F15*$C$6 -> 115000 | H15: =D15*$C$4+E15*$C$5 -> 22000 | I15: =G15+H15 -> 137000 | J15: =B15*$D$2+C15*$D$3+D15*$D$4+E15*$D$5+F15*$D$6 -> 159
A16: 7 | B16: 1 | C16: 1 | D16: 6 | E16: 1 | F16: 3 | G16: =B16*$C$2+C16*$C$3+F16*$C$6 -> 115000 | H16: =D16*$C$4+E16*$C$5 -> 27000 | I16: =G16+H16 -> 142000 | J16: =B16*$D$2+C16*$D$3+D16*$D$4+E16*$D$5+F16*$D$6 -> 164
A17: 8 | B17: 1 | C17: 1 | D17: 6 | E17: 1 | F17: 3 | G17: =B17*$C$2+C17*$C$3+F17*$C$6 -> 115000 | H17: =D17*$C$4+E17*$C$5 -> 27000 | I17: =G17+H17 -> 142000 | J17: =B17*$D$2+C17*$D$3+D17*$D$4+E17*$D$5+F17*$D$6 -> 164
A18: 9 | B18: 1 | C18: 1 | D18: 6 | E18: 1 | F18: 4 | G18: =B18*$C$2+C18*$C$3+F18*$C$6 -> 130000 | H18: =D18*$C$4+E18*$C$5 -> 27000 | I18: =G18+H18 -> 157000 | J18: =B18*$D$2+C18*$D$3+D18*$D$4+E18*$D$5+F18*$D$6 -> 183
A19: 10 | B19: 1 | C19: 1 | D19: 6 | E19: 1 | F19: 4 | G19: =B19*$C$2+C19*$C$3+F19*$C$6 -> 130000 | H19: =D19*$C$4+E19*$C$5 -> 27000 | I19: =G19+H19 -> 157000 | J19: =B19*$D$2+C19*$D$3+D19*$D$4+E19*$D$5+F19*$D$6 -> 183
A20: 11 | B20: 1 | C20: 1 | D20: 6 | E20: 1 | F20: 4 | G20: =B20*$C$2+C20*$C$3+F20*$C$6 -> 130000 | H20: =D20*$C$4+E20*$C$5 -> 27000 | I20: =G20+H20 -> 157000 | J20: =B20*$D$2+C20*$D$3+D20*$D$4+E20*$D$5+F20*$D$6 -> 183
A21: 12 | B21: 1 | C21: 1 | D21: 6 | E21: 1 | F21: 4 | G21: =B21*$C$2+C21*$C$3+F21*$C$6 -> 130000 | H21: =D21*$C$4+E21*$C$5 -> 27000 | I21: =G21+H21 -> 157000 | J21: =B21*$D$2+C21*$D$3+D21*$D$4+E21*$D$5+F21*$D$6 -> 183
... A45: 36 | B45: 2 | C45: 1 | D45: 10 | E45: 2 | F45: 6 | G45: =B45*$C$2+C45*$C$3+F45*$C$6 -> 185000 | H45: =D45*$C$4+E45*$C$5 -> 49000 | I45: =G45+H45 -> 234000 | J45: =B45*$D$2+C45*$D$3+D45*$D$4+E45*$D$5+F45*$D$6 -> 273
A46: Разом | G46: =SUM(G10:G45) -> 5280000 | H46: =SUM(H10:H45) -> 1266000 | I46: =SUM(I10:I45) -> 6546000
A47: Довідково: 3 фахівці × ~120 оплачуваних годин/міс = ~360 год; максимальне навантаження у моделі перевірте у колонці J.

Sheet Помісячний план
A1: Місяць | B1: Дохід від послуг | C1: Грант | D1: Власні кошти | E1: Разом надходжень | F1: Грантові закупівлі | G1: Навчання (власні) | H1: Оренда | I1: Інші поточні витрати | J1: Зарплата нарахована | K1: ЄСВ роботодавця | L1: ПДФО | M1: ВЗ працівників | N1: ЄП 5 % | O1: ВЗ ФОП 1 % | P1: ЄСВ ФОП | Q1: Вилучення власниці | R1: Разом виплат | S1: Залишок на кінець місяця | T1: Податки та ЄСВ за місяць | U1: Накопичені податки | V1: Залишок зобов'язання за грантом
A2: 1 | B2: 62000 | C2: 1000000 | D2: 210000 | E2: =B2+C2+D2 -> 1272000 | F2: 1000000 | G2: 110000 | H2: 180000 | I2: -170000 | J2: 45000 | K2: =J2*Припущення!$B$10 -> 9900 | L2: =J2*Припущення!$B$8 -> 8100 | M2: =J2*Припущення!$B$9 -> 2250 | N2: =B2*Припущення!$B$6 -> 3100 | O2: =B2*Припущення!$B$7 -> 620 | P2: 2100.12 | Q2: 0 | R2: =F2+G2+H2+I2+J2+K2+N2+O2+P2+Q2 -> 1180720.1 | S2: =E2-R2 -> 91279.88 | T2: =K2+L2+M2+N2+O2+P2 -> 26070.12 | U2: =T2 -> 26070.12 | V2: =MAX(0,Припущення!$B$4-U2) -> 973929.88
A3: 2 | B3: 62000 | C3: 0 | D3: 0 | E3: =B3+C3+D3 -> 62000 | F3: 0 | G3: 0 | H3: 0 | I3: 13000 | J3: 45000 | K3: =J3*Припущення!$B$10 -> 9900 | L3: =J3*Припущення!$B$8 -> 8100 | M3: =J3*Припущення!$B$9 -> 2250 | N3: =B3*Припущення!$B$6 -> 3100 | O3: =B3*Припущення!$B$7 -> 620 | P3: 2100.12 | Q3: 0 | R3: =F3+G3+H3+I3+J3+K3+N3+O3+P3+Q3 -> 73720.12 | S3: =S2+E3-R3 -> 79559.76 | T3: =K3+L3+M3+N3+O3+P3 -> 26070.12 | U3: =U2+T3 -> 52140.24 | V3: =MAX(0,Припущення!$B$4-U3) -> 947859.76
A4: 3 | B4: 77000 | C4: 0 | D4: 0 | E4: =B4+C4+D4 -> 77000 | F4: 0 | G4: 0 | H4: 0 | I4: 13000 | J4: 45000 | K4: =J4*Припущення!$B$10 -> 9900 | L4: =J4*Припущення!$B$8 -> 8100 | M4: =J4*Припущення!$B$9 -> 2250 | N4: =B4*Припущення!$B$6 -> 3850 | O4: =B4*Припущення!$B$7 -> 770 | P4: 2100.12 | Q4: 0 | R4: =F4+G4+H4+I4+J4+K4+N4+O4+P4+Q4 -> 74620.12 | S4: =S3+E4-R4 -> 81939.64 | T4: =K4+L4+M4+N4+O4+P4 -> 26970.12 | U4: =U3+T4 -> 79110.36 | V4: =MAX(0,Припущення!$B$4-U4) -> 920889.64
A5: 4 | B5: 77000 | C5: 0 | D5: 0 | E5: =B5+C5+D5 -> 77000 | F5: 0 | G5: 0 | H5: 0 | I5: 13000 | J5: 45000 | K5: =J5*Припущення!$B$10 -> 9900 | L5: =J5*Припущення!$B$8 -> 8100 | M5: =J5*Припущення!$B$9 -> 2250 | N5: =B5*Припущення!$B$6 -> 3850 | O5: =B5*Припущення!$B$7 -> 770 | P5: 2100.12 | Q5: 10000 | R5: =F5+G5+H5+I5+J5+K5+N5+O5+P5+Q5 -> 84620.12 | S5: =S4+E5-R5 -> 74319.52 | T5: =K5+L5+M5+N5+O5+P5 -> 26970.12 | U5: =U4+T5 -> 106080.48 | V5: =MAX(0,Припущення!$B$4-U5) -> 893919.52
A6: 5 | B6: 77000 | C6: 0 | D6: 0 | E6: =B6+C6+D6 -> 77000 | F6: 0 | G6: 0 | H6: 0 | I6: 13000 | J6: 45000 | K6: =J6*Припущення!$B$10 -> 9900 | L6: =J6*Припущення!$B$8 -> 8100 | M6: =J6*Припущення!$B$9 -> 2250 | N6: =B6*Припущення!$B$6 -> 3850 | O6: =B6*Припущення!$B$7 -> 770 | P6: 2100.12 | Q6: 10000 | R6: =F6+G6+H6+I6+J6+K6+N6+O6+P6+Q6 -> 84620.12 | S6: =S5+E6-R6 -> 66699.4 | T6: =K6+L6+M6+N6+O6+P6 -> 26970.12 | U6: =U5+T6 -> 133050.6 | V6: =MAX(0,Припущення!$B$4-U6) -> 866949.4
A7: 6 | B7: 137000 | C7: 0 | D7: 0 | E7: =B7+C7+D7 -> 137000 | F7: 0 | G7: 0 | H7: 0 | I7: 13000 | J7: 45000 | K7: =J7*Припущення!$B$10 -> 9900 | L7: =J7*Припущення!$B$8 -> 8100 | M7: =J7*Припущення!$B$9 -> 2250 | N7: =B7*Припущення!$B$6 -> 6850 | O7: =B7*Припущення!$B$7 -> 1370 | P7: 2100.12 | Q7: 10000 | R7: =F7+G7+H7+I7+J7+K7+N7+O7+P7+Q7 -> 88220.12 | S7: =S6+E7-R7 -> 115479.28 | T7: =K7+L7+M7+N7+O7+P7 -> 30570.12 | U7: =U6+T7 -> 163620.72 | V7: =MAX(0,Припущення!$B$4-U7) -> 836379.28
A8: 7 | B8: 142000 | C8: 0 | D8: 0 | E8: =B8+C8+D8 -> 142000 | F8: 0 | G8: 0 | H8: 0 | I8: 15000 | J8: 45000 | K8: =J8*Припущення!$B$10 -> 9900 | L8: =J8*Припущення!$B$8 -> 8100 | M8: =J8*Припущення!$B$9 -> 2250 | N8: =B8*Припущення!$B$6 -> 7100 | O8: =B8*Припущення!$B$7 -> 1420 | P8: 2100.12 | Q8: 10000 | R8: =F8+G8+H8+I8+J8+K8+N8+O8+P8+Q8 -> 90520.12 | S8: =S7+E8-R8 -> 166959.16 | T8: =K8+L8+M8+N8+O8+P8 -> 30870.12 | U8: =U7+T8 -> 194490.84 | V8: =MAX(0,Припущення!$B$4-U8) -> 805509.16
A9: 8 | B9: 142000 | C9: 0 | D9: 0 | E9: =B9+C9+D9 -> 142000 | F9: 0 | G9: 0 | H9: 0 | I9: 15000 | J9: 45000 | K9: =J9*Припущення!$B$10 -> 9900 | L9: =J9*Припущення!$B$8 -> 8100 | M9: =J9*Припущення!$B$9 -> 2250 | N9: =B9*Припущення!$B$6 -> 7100 | O9: =B9*Припущення!$B$7 -> 1420 | P9: 2100.12 | Q9: 10000 | R9: =F9+G9+H9+I9+J9+K9+N9+O9+P9+Q9 -> 90520.12 | S9: =S8+E9-R9 -> 218439.04 | T9: =K9+L9+M9+N9+O9+P9 -> 30870.12 | U9: =U8+T9 -> 225360.96 | V9: =MAX(0,Припущення!$B$4-U9) -> 774639.04
A10: 9 | B10: 157000 | C10: 0 | D10: 0 | E10: =B10+C10+D10 -> 157000 | F10: 0 | G10: 0 | H10: 0 | I10: 15000 | J10: 45000 | K10: =J10*Припущення!$B$10 -> 9900 | L10: =J10*Припущення!$B$8 -> 8100 | M10: =J10*Припущення!$B$9 -> 2250 | N10: =B10*Припущення!$B$6 -> 7850 | O10: =B10*Припущення!$B$7 -> 1570 | P10: 2100.12 | Q10: 10000 | R10: =F10+G10+H10+I10+J10+K10+N10+O10+P10+Q10 -> 91420.12 | S10: =S9+E10-R10 -> 284018.92 | T10: =K10+L10+M10+N10+O10+P10 -> 31770.12 | U10: =U9+T10 -> 257131.08 | V10: =MAX(0,Припущення!$B$4-U10) -> 742868.92
A11: 10 | B11: 157000 | C11: 0 | D11: 0 | E11: =B11+C11+D11 -> 157000 | F11: 0 | G11: 0 | H11: 0 | I11: 15000 | J11: 45000 | K11: =J11*Припущення!$B$10 -> 9900 | L11: =J11*Припущення!$B$8 -> 8100 | M11: =J11*Припущення!$B$9 -> 2250 | N11: =B11*Припущення!$B$6 -> 7850 | O11: =B11*Припущення!$B$7 -> 1570 | P11: 2100.12 | Q11: 10000 | R11: =F11+G11+H11+I11+J11+K11+N11+O11+P11+Q11 -> 91420.12 | S11: =S10+E11-R11 -> 349598.8 | T11: =K11+L11+M11+N11+O11+P11 -> 31770.12 | U11: =U10+T11 -> 288901.2 | V11: =MAX(0,Припущення!$B$4-U11) -> 711098.8
A12: 11 | B12: 157000 | C12: 0 | D12: 0 | E12: =B12+C12+D12 -> 157000 | F12: 0 | G12: 0 | H12: 0 | I12: 15000 | J12: 45000 | K12: =J12*Припущення!$B$10 -> 9900 | L12: =J12*Припущення!$B$8 -> 8100 | M12: =J12*Припущення!$B$9 -> 2250 | N12: =B12*Припущення!$B$6 -> 7850 | O12: =B12*Припущення!$B$7 -> 1570 | P12: 2100.12 | Q12: 10000 | R12: =F12+G12+H12+I12+J12+K12+N12+O12+P12+Q12 -> 91420.12 | S12: =S11+E12-R12 -> 415178.68 | T12: =K12+L12+M12+N12+O12+P12 -> 31770.12 | U12: =U11+T12 -> 320671.32 | V12: =MAX(0,Припущення!$B$4-U12) -> 679328.68
A13: 12 | B13: 157000 | C13: 0 | D13: 0 | E13: =B13+C13+D13 -> 157000 | F13: 0 | G13: 0 | H13: 0 | I13: 13000 | J13: 45000 | K13: =J13*Припущення!$B$10 -> 9900 | L13: =J13*Припущення!$B$8 -> 8100 | M13: =J13*Припущення!$B$9 -> 2250 | N13: =B13*Припущення!$B$6 -> 7850 | O13: =B13*Припущення!$B$7 -> 1570 | P13: 2100.12 | Q13: 10000 | R13: =F13+G13+H13+I13+J13+K13+N13+O13+P13+Q13 -> 89420.12 | S13: =S12+E13-R13 -> 482758.56 | T13: =K13+L13+M13+N13+O13+P13 -> 31770.12 | U13: =U12+T13 -> 352441.44 | V13: =MAX(0,Припущення!$B$4-U13) -> 647558.56
A14: 13 | B14: 187000 | C14: 0 | D14: 275860 | E14: =B14+C14+D14 -> 462860 | F14: 0 | G14: 275860 | H14: 15000 | I14: 30000 | J14: 50000 | K14: =J14*Припущення!$B$10 -> 11000 | L14: =J14*Припущення!$B$8 -> 9000 | M14: =J14*Припущення!$B$9 -> 2500 | N14: =B14*Припущення!$B$6 -> 9350 | O14: =B14*Припущення!$B$7 -> 1870 | P14: 2100.12 | Q14: 25000 | R14: =F14+G14+H14+I14+J14+K14+N14+O14+P14+Q14 -> 420180.12 | S14: =S13+E14-R14 -> 525438.44 | T14: =K14+L14+M14+N14+O14+P14 -> 35820.12 | U14: =U13+T14 -> 388261.56 | V14: =MAX(0,Припущення!$B$4-U14) -> 611738.44
... A37: 36 | B37: 234000 | C37: 0 | D37: 0 | E37: =B37+C37+D37 -> 234000 | F37: 0 | G37: 0 | H37: 15000 | I37: 30000 | J37: 55000 | K37: =J37*Припущення!$B$10 -> 12100 | L37: =J37*Припущення!$B$8 -> 9900 | M37: =J37*Припущення!$B$9 -> 2750 | N37: =B37*Припущення!$B$6 -> 11700 | O37: =B37*Припущення!$B$7 -> 2340 | P37: 2100.12 | Q37: 35000 | R37: =F37+G37+H37+I37+J37+K37+N37+O37+P37+Q37 -> 163240.12 | S37: =S36+E37-R37 -> 1908635.7 | T37: =K37+L37+M37+N37+O37+P37 -> 40890.12 | U37: =U36+T37 -> 1278364.3 | V37: =MAX(0,Припущення!$B$4-U37) -> 0
A38: Разом | B38: =SUM(B2:B37) -> 6546000 | C38: =SUM(C2:C37) -> 1000000 | D38: =SUM(D2:D37) -> 485860 | E38: =SUM(E2:E37) -> 8031860 | F38: =SUM(F2:F37) -> 1000000 | G38: =SUM(G2:G37) -> 385860 | H38: =SUM(H2:H37) -> 540000 | I38: =SUM(I2:I37) -> 723000 | ... R38: =SUM(R2:R37) -> 6123224.3 | T38: =SUM(T2:T37) -> 1278364.3
A40: Покриття гранту податками (місяць, коли накопичені податки ≥ грант): | E40: =IFERROR(MATCH(0,V2:V37,0),"не покрито") -> 30
A41: Мінімальний залишок коштів за 36 місяців, грн: | E41: =MIN(S2:S37) -> 66699.4

Sheet Сценарії
A1: Сценарій | B1: Дохід за 36 міс | C1: Податки та ЄСВ за 36 міс | D1: Покриття гранту | E1: Мінімальний залишок коштів | F1: Операційний прибуток | G1: Коментар
A2: Базовий | B2: 6546000 | C2: 1278364 | D2: М30 | E2: 66699 | F2: 2618636 | G2: консервативний план продажів; 2 працівники з М1
A3: Дохід −20 % | B3: 5236800 | C3: 1199812 | D3: М31 | E3: -41 | F3: 1387988 | G3: перевірка умови «податки ≥ грант» за падіння виручки
A4: Дохід −30 % | B4: 4582200 | C4: 1160536 | D4: М32 | E4: -33411 | F4: 772664 | G4: податки все ще ≥ гранту, але касовий розрив у перші місяці — потрібен більший резерв або менші вилучення
A5: Старт продажів на 3 місяці пізніше | B5: 6345000 | C5: 1266304 | D5: М30 | E5: -122241 | F5: 2429696 | G5: витрати на команду з М1, дохід з М4; показує потребу в резерві
A6: Зарплати +15 % | B6: 6546000 | C6: 1399864 | D6: М28 | E6: 25524 | F6: 2289236 | G6: податки зростають, умова виконується з запасом; тисне на прибуток
A9: Висновок: у всіх сценаріях сума сплачених податків і ЄСВ за 36 місяців перевищує грант 1 000 000 грн (запас у базовому — 28 %). Слабке місце — ліквідність у М2–М6 за падіння виручки або пізнього старту: тримати резерв не менше 150 000 грн і мінімальні вилучення в перший рік.

Sheet Оцінка балів (дод. 3)
A1: № | B1: Критерій (для фізичних осіб / ФОП) | C1: Варіанти та бали з коефіцієнтом | D1: Що впливає / що може зробити заявниця | E1: Обраний варіант (бали)
A2: 1 | B2: Кількість погашених кредитів | C2: 0 — 0; 1–3 — 10; 4–5 — 14; >5 — 20 | D2: Факт кредитної історії. Не брати кредити заради балів. | E2: 0
A3: 2 | B3: Максимальний строк прострочення (сума > 1000 грн, за 3 роки) | C3: 0 днів — 20; 1–15 — 14; 16–30 — 10; 31–60 — 2; >60 — 0; позик не було — 10 | D3: Погасити будь-які прострочення до подання заяви; взяти кредитний звіт в УБКІ/ПВБКІ. | E3: 10
A4: 3 | B4: Кількість прострочень < 90 днів за 2 роки | C4: 0 — 20; 1–3 — 10; >3 — 0 | E4: 20
A5: 4 | B5: Кількість запитів на кредит за 12 міс | C5: <2 — 15; 3 — 11; 4 — 5; ≥5 — 0 | D5: Не подавати кредитних заявок за 12 місяців до подання. | E5: 15
A6: 5 | B6: Місячний платіж за кредитами / дохід | C6: <0,1 — 14; 0,1–0,24 — 10; 0,25–0,5 — 7; >0,5 — 0 | E6: 14
A7: 6 | B7: Створення нових робочих місць | C7: 0 — 0; 1 — 1; 2 — 3; >2 — 4 | D7: У плані 2 нових місця — 3 бали. | E7: 3
A8: 7 | B8: Очікувана рентабельність за бізнес-планом | C8: >0,5 — 6; 0,3–0,5 — 4; 0,15–0,3 — 3; <0,15 — 0 | D8: У плані 67 % — 6 балів. | E8: 6
A9: 8 | B9: Період окупності, років | C9: <1 — 4; ≈3 — 3; ≥5 — 0 | D9: У плані 1,7 року — очікувано 3–4 бали. | E9: 3
A10: 9 | B10: Участь власними коштами | C10: >0,5 — 20; 0,3–0,5 — 4 (у наказі, ймовірно, 14); 0,15–0,3 — 3; <0,15 — 0 | D10: У плані 33 % — підтвердити випискою; збільшення власної участі до >50 % дало б 20 балів. | E10: 4
A11: 10 | B11: Нерухомість для бізнесу | C11: не потрібна — 10; власна (у т. ч. подружжя) — 10; родичів — 7; оренда >1 року — 4; оренда <1 року — 0 | D11: Укласти договір оренди на 12+ місяців до подання (4 бали) або використати власне/родинне приміщення (10/7). | E11: 4
A12: 11 | B12: Транспорт для бізнесу | C12: не потрібен — 10; власний — 7; родичів — 5; орендований — 0 | D12: Для консалтингу транспорт не потрібен — 10. | E12: 10
A13: 12 | B13: Сімейний стан | C13: одружена — 4; розлучена — 2; не у шлюбі / цивільний шлюб — 0 | D13: Факт.
A14: 13 | B14: Утриманці (неповнолітні діти) | C14: немає — 10; 1 — 5; 2+ — 0 | D14: Факт.
A15: 14 | B15: Активи у власності | C15: житло у власності (у т. ч. подружжя) — 10; у родичів — 7; оренда — 0; авто у власності — 5; авто родичів — 3 | D15: Факт; зазначити у заяві все, що є.
A16: 15 | B16: Вік | C16: 18–25 — 2; 26–45 — 3; 46–55 — 4; >55 — 2 | D16: Факт.
A17: 16 | B17: Стаж за попереднім/поточним місцем роботи | C17: <5 років — 0; 5–12 — 2; >12 — 4 | D17: Стаж директора ліцею — зазначити у заяві.
A18: 17 | B18: Користування послугами банку | C18: немає рахунків — 0; поточний/картковий — 2; кредити — 3; депозит — 5 | D18: Відкрити депозит в обраному уповноваженому банку до подання — 5 балів. | E18: 5
A19: 18 | B19: Освіта | C19: бакалавр — 2; магістр/спеціаліст — 3; аспірантура/PhD — 4; профтехосвіта — 2; 11 класів — 1 | D19: Факт; вказати найвищий рівень.
A20: 19 | B20: Тип населеного пункту | C20: <20 тис. — 0; 20–200 тис. — 1; 200–500 тис. — 2; 0,5–1 млн — 3; >1 млн — 3; >2 млн — 4 | D20: Жашків (<20 тис.) — 0. Не змінювати місце реєстрації заради балів. | E20: 0
A21: 20 | B21: Цивільні судові справи | C21: є — 0; немає — 2 | D21: Перевірити себе в реєстрі судових рішень та YouControl. | E21: 2
A22: 21 | B22: Ризик виду діяльності (експертне судження банку) | C22: низький — 10; середній — 5; високий — 0 | D22: Консалтинг — зазвичай низький/середній. | E22: 5
B23: Разом балів банку (максимум 200; прохідний поріг 99) | E23: =SUM(E2:E22) -> 101
B24: Співбесіда (0–50): мотивація, розуміння бізнес-плану, маркетингового плану, операційного плану, релевантний досвід — по 0/3/5/7/10 | E24: 35
B25: Підсумковий бал (поріг 130 з 250) | E25: =E23+E24 -> 136
B27: Порожні клітинки у колонці E — особисті дані, які відомі лише заявниці; заповніть їх, щоб побачити власну оцінку. Джерело: додаток 3 і додаток 5 до наказу Мінекономіки від 22.07.2026 № 2 (зареєстровано Мін'юстом 28.08.2026 за № 1185/46579).

Sheet Ліміти п.7
A1: Стаття інвестиційного плану | B1: Сума, грн | C1: Частка гранту | D1: Ліміт п. 7 Порядку | E1: Статус
A2: Комп'ютерна техніка та обладнання робочих місць | B2: 300000 | C2: =B2/Припущення!$B$4 -> 0.3 | D2: без окремого ліміту | E2: у межах
A3: Меблі для 3 робочих місць і переговорної зони | B3: 90000 | C3: =B3/Припущення!$B$4 -> 0.09 | D3: без окремого ліміту | E3: у межах
A4: Ліцензійне програмне забезпечення (12 місяців) | B4: 180000 | C4: =B4/Припущення!$B$4 -> 0.18 | D4: не більше 25% | E4: =IF(C4<=0.25,"у межах","ПЕРЕВИЩЕНО") -> у межах
A5: Вебсайт із базою знань та інтеграцією з CRM | B5: 95000 | C5: =B5/Припущення!$B$4 -> 0.095 | D5: не більше 10% | E5: =IF(C5<=0.1,"у межах","ПЕРЕВИЩЕНО") -> у межах
A6: Налаштування та інтеграція цифрових рішень | B6: 40000 | C6: =B6/Припущення!$B$4 -> 0.04 | D6: не більше 20% | E6: =IF(C6<=0.2,"у межах","ПЕРЕВИЩЕНО") -> у межах
A7: Маркетинг та реклама | B7: 95000 | C7: =B7/Припущення!$B$4 -> 0.095 | D7: не більше 10% | E7: =IF(C7<=0.1,"у межах","ПЕРЕВИЩЕНО") -> у межах
A8: Фірмовий стиль і промоматеріали | B8: 20000 | C8: =B8/Припущення!$B$4 -> 0.02 | D8: не більше 50% | E8: =IF(C8<=0.5,"у межах","ПЕРЕВИЩЕНО") -> у межах
A9: Оренда офісного приміщення (12 місяців) | B9: 180000 | C9: =B9/Припущення!$B$4 -> 0.18 | D9: не більше 25% | E9: =IF(C9<=0.25,"у межах","ПЕРЕВИЩЕНО") -> у межах
A10: Разом | B10: =SUM(B2:B9) -> 1000000 | E10: =IF(B10=Припущення!$B$4,"= грант","≠ грант") -> = грант
